{
  "formatVersion": 1,
  "database": {
    "version": 2,
    "identityHash": "a006f64653c2e33bd384ecf56826745d",
    "entities": [
      {
        "tableName": "tv_shows",
        "createSql": "CREATE TABLE IF NOT EXISTS `${TABLE_NAME}` (`id` INTEGER NOT NULL, `title` TEXT NOT NULL, `status` TEXT NOT NULL, `imageUrl` TEXT NOT NULL, `summary` TEXT NOT NULL, `rating` REAL NOT NULL, PRIMARY KEY(`id`))",
        "fields": [
          {
            "fieldPath": "id",
            "columnName": "id",
            "affinity": "INTEGER",
            "notNull": true
          },
          {
            "fieldPath": "title",
            "columnName": "title",
            "affinity": "TEXT",
            "notNull": true
          },
          {
            "fieldPath": "status",
            "columnName": "status",
            "affinity": "TEXT",
            "notNull": true
          },
          {
            "fieldPath": "imageUrl",
            "columnName": "imageUrl",
            "affinity": "TEXT",
            "notNull": true
          },
          {
            "fieldPath": "summary",
            "columnName": "summary",
            "affinity": "TEXT",
            "notNull": true
          },
          {
            "fieldPath": "rating",
            "columnName": "rating",
            "affinity": "REAL",
            "notNull": true
          }
        ],
        "primaryKey": {
          "columnNames": [
            "id"
          ],
          "autoGenerate": false
        },
        "indices": [],
        "foreignKeys": []
      }
    ],
    "views": [],
    "setupQueries": [
      "CREATE TABLE IF NOT EXISTS room_master_table (id INTEGER PRIMARY KEY,identity_hash TEXT)",
      "INSERT OR REPLACE INTO room_master_table (id,identity_hash) VALUES(42, 'a006f64653c2e33bd384ecf56826745d')"
    ]
  }
}